bd_map_plotter/__init__.py
bd_map_plotter/border_map.py
bd_map_plotter/divisions_map.py
bd_map_plotter/data/border_map.json
bd_map_plotter/data/districts_map.json
bd_map_plotter/data/divisions_map.json
bd_map_plotter/data/subdistricts_map.json
bd_map_plotter/data/union_map.json
bd_map_plotter-0.2.dist-info/METADATA
bd_map_plotter-0.2.dist-info/WHEEL
bd_map_plotter-0.2.dist-info/top_level.txt
bd_map_plotter-0.2.dist-info/RECORD
